finnpy/basic/__init__.py
finnpy/basic/car.py
finnpy/basic/downsampling.py
finnpy/cfc/__init__.py
finnpy/cfc/pac.py
finnpy/cleansing/__init__.py
finnpy/cleansing/bad_channel_identification.py
finnpy/cleansing/channel_restoration.py
finnpy/cleansing/neighboring_channels.py
finnpy/cleansing/outlier_removal.py
finnpy/file_io/__init__.py
finnpy/file_io/csv_data.py
finnpy/file_io/data_manager.py
finnpy/file_io/data_manager_legacy.py
finnpy/file_io/load_brainvision_data.py
finnpy/file_io/nifti_data.py
finnpy/filters/__init__.py
finnpy/filters/frequency.py
finnpy/misc/__init__.py
finnpy/misc/timed_pool.py
finnpy/sfc/__init__.py
finnpy/sfc/_dac.py
finnpy/sfc/_misc.py
finnpy/sfc/_psi.py
finnpy/sfc/_wpli.py
finnpy/sfc/cd.py
finnpy/sfc/fd.py
finnpy/sfc/td.py
finnpy/statistical/__init__.py
finnpy/statistical/glmm.py
finnpy/visualization/__init__.py
finnpy/visualization/coord_map.ods
finnpy/visualization/topoplot.py
finnpy/visualization/volumetric_plots.py
finnpy-2.0.0.dist-info/LICENSE
finnpy-2.0.0.dist-info/METADATA
finnpy-2.0.0.dist-info/WHEEL
finnpy-2.0.0.dist-info/top_level.txt
finnpy-2.0.0.dist-info/RECORD
