Metadata-Version: 2.1
Name: finnpy
Version: 2.0.0
Summary: Toolbox for the analysis of electrophysiological data
Home-page: https://github.com/neurophysiological-analysis/FiNN
Download-URL: https://github.com/neurophysiological-analysis/FiNN
Author: Maximilian Scherer
Author-email: maximilian.scherer@posteo.net
License: GPLv3
Classifier: Development Status :: 5 - Production/Stable
Classifier: Environment :: Console
Classifier: Intended Audience :: Developers
Classifier: Intended Audience :: Education
Classifier: Intended Audience :: Healthcare Industry
Classifier: Intended Audience :: Science/Research
Classifier: Intended Audience :: Information Technology
Classifier: License :: OSI Approved :: GNU General Public License v3 (GPLv3)
Classifier: Operating System :: OS Independent
Classifier: Programming Language :: Python
Classifier: Programming Language :: Python :: 3
Classifier: Topic :: Scientific/Engineering :: Human Machine Interfaces
Classifier: Topic :: Scientific/Engineering :: Medical Science Apps.
Classifier: Topic :: Software Development :: Libraries
Requires-Python: >=3.8
License-File: LICENSE
Requires-Dist: numpy
Requires-Dist: scipy
Requires-Dist: lmfit
Requires-Dist: PyQt6
Requires-Dist: matplotlib
Requires-Dist: mne
Requires-Dist: rpy2
Requires-Dist: scikit-image
Requires-Dist: pyexcel-ods
